{
  "$schema": "https://developer.microsoft.com/json-schemas/spfx-build/package-solution.schema.json",
  "solution": {
    "name": "spfx-extension-insert-css",
    "id": "47c9c910-9bd5-4884-bc44-4d95629a2fd5",
    "version": "1.0.0.0",
    "includeClientSideAssets": true,
    "skipFeatureDeployment": true,
    "isDomainIsolated": false,
    "developer": {
      "name": "Julien Aubert",
      "websiteUrl": "",
      "privacyUrl": "",
      "termsOfUseUrl": "",
      "mpnId": "Undefined-1.18.2"
    },
    "metadata": {
      "shortDescription": {
        "default": "spfx-extension-insert-css"
      },
      "longDescription": {
        "default": "spfx extension to insert custom css"
      },
      "screenshotPaths": [],
      "videoUrl": "",
      "categories": []
    },
    "features": [
      {
        "title": "Application Extension - Deployment of custom css",
        "description": "Deploys a custom css where the feature is activated",
        "id": "28673580-f854-4f5c-9df8-82e8e0ab6f0c",
        "version": "1.0.0.0",
        "assets": {
          "elementManifests": [
            "elements.xml",
            "ClientSideInstance.xml"
          ]
        }
      }
    ]
  },
  "paths": {
    "zippedPackage": "solution/spfx-extension-insert-css.sppkg"
  }
}
